{
  "industry": "eVTOL & Advanced Air Mobility",
  "generated_at": "2025-11-18T23:00:00.000000Z",
  "analysis_type": "consensus_combined",
  "metadata": {
    "date_from": "2020-01-01",
    "date_to": "2025-11-18",
    "phases": {
      "innovation_trigger": 5,
      "peak": 12,
      "trough": 10,
      "slope": 12,
      "plateau": 11
    },
    "consensus_config": {
      "source_analyses": 2,
      "total_unique_technologies": 50,
      "overlap_technologies": 16,
      "methodology": "weighted_average_with_recency_bias"
    },
    "graph_data": {
      "communities": {
        "total": 158,
        "versions": {"v0": 59, "v1": 49, "v2": 50}
      },
      "documents": {
        "total": 2099,
        "by_type": {
          "patent": 732,
          "news": 262,
          "technical_paper": 535,
          "government_contract": 206,
          "sec_filing": 338,
          "github": 21
        }
      },
      "technologies": {
        "total": 1755,
        "with_documents": 1755,
        "consensus_selected": 50
      },
      "companies": {"total": 122},
      "relationships": {
        "total": 21516,
        "mentioned_in": 7425,
        "belongs_to_community": 9943
      }
    }
  },
  "technologies": [
    {
      "id": "friction_welding_process",
      "name": "Friction Welding Process",
      "domain": "Manufacturing",
      "phase": "Innovation Trigger",
      "phase_position": "late",
      "phase_confidence": 0.85,
      "chart_x": 0.6,
      "scores": {
        "innovation": 45.0,
        "adoption": 10.0,
        "narrative": 35.0,
        "risk": 15.0,
        "hype": 52.28
      },
      "consensus_note": "Highest innovation score - critical manufacturing breakthrough",
      "evidence_counts": {"patents": 19, "papers": 0}
    },
    {
      "id": "flight_control_system",
      "name": "Flight Control System",
      "domain": "Control Systems",
      "phase": "Innovation Trigger",
      "phase_position": "late",
      "phase_confidence": 0.65,
      "chart_x": 0.35,
      "scores": {
        "innovation": 25.0,
        "adoption": 10.0,
        "narrative": 40.0,
        "risk": 20.0,
        "hype": 25.0
      },
      "evidence_counts": {"patents": 2, "papers": 2}
    },
    {
      "id": "battery_compression_system",
      "name": "Battery Compression System",
      "domain": "Energy Storage",
      "phase": "Innovation Trigger",
      "phase_position": "early",
      "phase_confidence": 0.65,
      "chart_x": 0.1,
      "scores": {
        "innovation": 25.0,
        "adoption": 10.0,
        "narrative": 35.0,
        "risk": 15.0,
        "hype": 27.83
      },
      "evidence_counts": {"patents": 2, "papers": 2}
    },
    {
      "id": "multi_stage_electric_fan_propulsion",
      "name": "Multi Stage Electric Fan Propulsion",
      "domain": "Propulsion",
      "phase": "Innovation Trigger",
      "phase_position": "late",
      "phase_confidence": 0.65,
      "chart_x": 0.4,
      "scores": {
        "innovation": 25.0,
        "adoption": 10.0,
        "narrative": 35.0,
        "risk": 15.0,
        "hype": 27.83
      },
      "evidence_counts": {"patents": 2, "papers": 0}
    },
    {
      "id": "route_optimization_system",
      "name": "Route Optimization System",
      "domain": "Operations",
      "phase": "Innovation Trigger",
      "phase_position": "late",
      "phase_confidence": 0.65,
      "chart_x": 0.5,
      "scores": {
        "innovation": 30.0,
        "adoption": 10.0,
        "narrative": 40.0,
        "risk": 15.0,
        "hype": 22.46
      },
      "consensus_note": "Critical for operational efficiency",
      "evidence_counts": {"patents": 1, "papers": 0}
    },
    {
      "id": "electric_air_taxi_services",
      "name": "Electric Air Taxi Services",
      "domain": "Operations",
      "phase": "Peak of Inflated Expectations",
      "phase_position": "late",
      "phase_confidence": 0.85,
      "chart_x": 1.08,
      "scores": {
        "innovation": 0.0,
        "adoption": 20.0,
        "narrative": 85.0,
        "risk": 17.5,
        "hype": 100.0
      },
      "consensus_note": "Maximum hype, minimal deployment",
      "evidence_counts": {"news": 18}
    },
    {
      "id": "evtol_transportation_network",
      "name": "eVTOL Transportation Network",
      "domain": "Infrastructure",
      "phase": "Peak of Inflated Expectations",
      "phase_position": "late",
      "phase_confidence": 0.85,
      "chart_x": 1.3,
      "scores": {
        "innovation": 5.0,
        "adoption": 10.0,
        "narrative": 95.0,
        "risk": 15.0,
        "hype": 100.0
      },
      "evidence_counts": {"papers": 1, "news": 4}
    },
    {
      "id": "electric_propulsion_vehicle",
      "name": "Electric Propulsion Vehicle",
      "domain": "Vehicle Systems",
      "phase": "Peak of Inflated Expectations",
      "phase_position": "mid",
      "phase_confidence": 0.85,
      "chart_x": 0.97,
      "scores": {
        "innovation": 27.5,
        "adoption": 20.0,
        "narrative": 85.0,
        "risk": 17.5,
        "hype": 100.0
      },
      "consensus_note": "Averaged innovation scores from both analyses",
      "evidence_counts": {"patents": 3, "papers": 4, "news": 2}
    },
    {
      "id": "digital_twin_technology",
      "name": "Digital Twin Technology",
      "domain": "Simulation",
      "phase": "Peak of Inflated Expectations",
      "phase_position": "early",
      "phase_confidence": 0.85,
      "chart_x": 0.86,
      "scores": {
        "innovation": 5.0,
        "adoption": 10.0,
        "narrative": 85.0,
        "risk": 15.0,
        "hype": 100.0
      },
      "consensus_note": "Critical for testing and validation",
      "evidence_counts": {"papers": 1, "news": 1}
    },
    {
      "id": "unmanned_aerial_vehicle_technology",
      "name": "Unmanned Aerial Vehicle Technology",
      "domain": "Platform Technology",
      "phase": "Peak of Inflated Expectations",
      "phase_position": "late",
      "phase_confidence": 0.85,
      "chart_x": 1.13,
      "scores": {
        "innovation": 10.0,
        "adoption": 10.0,
        "narrative": 95.0,
        "risk": 15.0,
        "hype": 100.0
      },
      "evidence_counts": {"papers": 1, "news": 1}
    },
    {
      "id": "autonomous_navigation_system",
      "name": "Autonomous Navigation System",
      "domain": "Autonomy",
      "phase": "Peak of Inflated Expectations",
      "phase_position": "early",
      "phase_confidence": 0.85,
      "chart_x": 0.8,
      "scores": {
        "innovation": 0.0,
        "adoption": 15.0,
        "narrative": 85.0,
        "risk": 15.0,
        "hype": 100.0
      },
      "evidence_counts": {"news": 1}
    },
    {
      "id": "all_electric_propulsion",
      "name": "All Electric Propulsion",
      "domain": "Propulsion",
      "phase": "Peak of Inflated Expectations",
      "phase_position": "late",
      "phase_confidence": 0.85,
      "chart_x": 1.13,
      "scores": {
        "innovation": 5.0,
        "adoption": 15.0,
        "narrative": 95.0,
        "risk": 15.0,
        "hype": 100.0
      },
      "evidence_counts": {"papers": 1, "news": 1}
    },
    {
      "id": "electric_drive_system",
      "name": "Electric Drive System",
      "domain": "Propulsion",
      "phase": "Peak of Inflated Expectations",
      "phase_position": "late",
      "phase_confidence": 0.85,
      "chart_x": 1.24,
      "scores": {
        "innovation": 17.5,
        "adoption": 10.0,
        "narrative": 95.0,
        "risk": 15.0,
        "hype": 100.0
      },
      "consensus_note": "Core propulsion technology",
      "evidence_counts": {"patents": 1, "papers": 1, "news": 2}
    },
    {
      "id": "hybrid_powerplant",
      "name": "Hybrid Powerplant",
      "domain": "Propulsion",
      "phase": "Peak of Inflated Expectations",
      "phase_position": "late",
      "phase_confidence": 0.85,
      "chart_x": 1.02,
      "scores": {
        "innovation": 0.0,
        "adoption": 10.0,
        "narrative": 90.0,
        "risk": 17.5,
        "hype": 100.0
      },
      "evidence_counts": {"news": 2}
    },
    {
      "id": "turbogenerator_power_source",
      "name": "Turbogenerator Power Source",
      "domain": "Power Systems",
      "phase": "Peak of Inflated Expectations",
      "phase_position": "mid",
      "phase_confidence": 0.85,
      "chart_x": 1.08,
      "scores": {
        "innovation": 0.0,
        "adoption": 10.0,
        "narrative": 90.0,
        "risk": 15.0,
        "hype": 100.0
      },
      "evidence_counts": {"news": 2}
    },
    {
      "id": "additive_manufacturing",
      "name": "Additive Manufacturing",
      "domain": "Manufacturing",
      "phase": "Trough of Disillusionment",
      "phase_position": "early",
      "phase_confidence": 0.85,
      "chart_x": 1.5,
      "scores": {
        "innovation": 0.0,
        "adoption": 10.0,
        "narrative": 35.0,
        "risk": 20.0,
        "hype": 20.14
      },
      "consensus_note": "Manufacturing maturity gap",
      "evidence_counts": {}
    },
    {
      "id": "automated_landing_abort_system",
      "name": "Automated Landing Abort System",
      "domain": "Safety Systems",
      "phase": "Trough of Disillusionment",
      "phase_position": "early",
      "phase_confidence": 0.85,
      "chart_x": 1.56,
      "scores": {
        "innovation": 0.0,
        "adoption": 10.0,
        "narrative": 35.0,
        "risk": 15.0,
        "hype": 20.56
      },
      "evidence_counts": {}
    },
    {
      "id": "detect_and_avoid",
      "name": "Detect And Avoid",
      "domain": "Safety Systems",
      "phase": "Trough of Disillusionment",
      "phase_position": "late",
      "phase_confidence": 0.85,
      "chart_x": 2.15,
      "scores": {
        "innovation": 0.0,
        "adoption": 15.0,
        "narrative": 40.0,
        "risk": 15.0,
        "hype": 38.54
      },
      "consensus_note": "Critical safety system lagging",
      "evidence_counts": {}
    },
    {
      "id": "autonomous_safety_system",
      "name": "Autonomous Safety System",
      "domain": "Safety Systems",
      "phase": "Trough of Disillusionment",
      "phase_position": "late",
      "phase_confidence": 0.85,
      "chart_x": 2.48,
      "scores": {
        "innovation": 0.0,
        "adoption": 17.5,
        "narrative": 37.5,
        "risk": 20.0,
        "hype": 36.56
      },
      "consensus_note": "Safety validation challenges",
      "evidence_counts": {}
    },
    {
      "id": "multidisciplinary_design_optimization",
      "name": "Multidisciplinary Design Optimization",
      "domain": "Design Tools",
      "phase": "Trough of Disillusionment",
      "phase_position": "late",
      "phase_confidence": 0.85,
      "chart_x": 2.7,
      "scores": {
        "innovation": 0.0,
        "adoption": 15.0,
        "narrative": 35.0,
        "risk": 15.0,
        "hype": 21.28
      },
      "evidence_counts": {}
    },
    {
      "id": "wind_tunnel_testing",
      "name": "Wind Tunnel Testing",
      "domain": "Testing",
      "phase": "Trough of Disillusionment",
      "phase_position": "late",
      "phase_confidence": 0.85,
      "chart_x": 2.29,
      "scores": {
        "innovation": 0.0,
        "adoption": 15.0,
        "narrative": 35.0,
        "risk": 17.5,
        "hype": 21.20
      },
      "evidence_counts": {}
    },
    {
      "id": "800v_electric_power_testbed",
      "name": "800V Electric Power Testbed",
      "domain": "Power Systems",
      "phase": "Trough of Disillusionment",
      "phase_position": "late",
      "phase_confidence": 0.65,
      "chart_x": 2.6,
      "scores": {
        "innovation": 0.0,
        "adoption": 20.0,
        "narrative": 30.0,
        "risk": 20.0,
        "hype": 24.83
      },
      "consensus_note": "High voltage system challenges",
      "evidence_counts": {}
    },
    {
      "id": "high_fidelity_simulation_model",
      "name": "High Fidelity Simulation Model",
      "domain": "Simulation",
      "phase": "Slope of Enlightenment",
      "phase_position": "early",
      "phase_confidence": 0.85,
      "chart_x": 2.94,
      "scores": {
        "innovation": 0.0,
        "adoption": 15.0,
        "narrative": 45.0,
        "risk": 17.5,
        "hype": 55.69
      },
      "evidence_counts": {}
    },
    {
      "id": "charging_infrastructure_for_batteries",
      "name": "Charging Infrastructure For Batteries",
      "domain": "Infrastructure",
      "phase": "Slope of Enlightenment",
      "phase_position": "early",
      "phase_confidence": 0.85,
      "chart_x": 2.95,
      "scores": {
        "innovation": 0.0,
        "adoption": 15.0,
        "narrative": 45.0,
        "risk": 15.0,
        "hype": 55.81
      },
      "consensus_note": "Infrastructure deployment beginning",
      "evidence_counts": {}
    },
    {
      "id": "high_power_lithium_ion_batteries",
      "name": "High Power Lithium Ion Batteries",
      "domain": "Energy Storage",
      "phase": "Slope of Enlightenment",
      "phase_position": "mid",
      "phase_confidence": 0.85,
      "chart_x": 2.87,
      "scores": {
        "innovation": 0.0,
        "adoption": 15.0,
        "narrative": 40.0,
        "risk": 22.5,
        "hype": 37.98
      },
      "consensus_note": "Transitioning between analyses",
      "evidence_counts": {}
    },
    {
      "id": "silicon_anode",
      "name": "Silicon Anode",
      "domain": "Energy Storage",
      "phase": "Slope of Enlightenment",
      "phase_position": "late",
      "phase_confidence": 0.85,
      "chart_x": 3.96,
      "scores": {
        "innovation": 0.0,
        "adoption": 20.0,
        "narrative": 45.0,
        "risk": 20.0,
        "hype": 55.14
      },
      "consensus_note": "Next-gen battery technology",
      "evidence_counts": {}
    },
    {
      "id": "aircraft_conflict_avoidance_system",
      "name": "Aircraft Conflict Avoidance System",
      "domain": "Safety Systems",
      "phase": "Slope of Enlightenment",
      "phase_position": "mid",
      "phase_confidence": 0.85,
      "chart_x": 3.22,
      "scores": {
        "innovation": 0.0,
        "adoption": 17.5,
        "narrative": 45.0,
        "risk": 17.5,
        "hype": 55.69
      },
      "consensus_note": "Regulatory progress",
      "evidence_counts": {}
    },
    {
      "id": "distributed_electric_propulsion",
      "name": "Distributed Electric Propulsion",
      "domain": "Propulsion",
      "phase": "Slope of Enlightenment",
      "phase_position": "late",
      "phase_confidence": 0.85,
      "chart_x": 3.4,
      "scores": {
        "innovation": 5.0,
        "adoption": 10.0,
        "narrative": 40.0,
        "risk": 25.0,
        "hype": 51.22
      },
      "consensus_note": "Novel architecture gaining traction",
      "evidence_counts": {"papers": 1}
    },
    {
      "id": "sustainable_aviation_practices",
      "name": "Sustainable Aviation Practices",
      "domain": "Operations",
      "phase": "Slope of Enlightenment",
      "phase_position": "late",
      "phase_confidence": 0.85,
      "chart_x": 3.71,
      "scores": {
        "innovation": 5.0,
        "adoption": 10.0,
        "narrative": 45.0,
        "risk": 25.0,
        "hype": 54.45
      },
      "consensus_note": "ESG driver",
      "evidence_counts": {"papers": 1}
    },
    {
      "id": "six_levels_of_autonomy",
      "name": "Six Levels Of Autonomy",
      "domain": "Autonomy",
      "phase": "Slope of Enlightenment",
      "phase_position": "late",
      "phase_confidence": 0.85,
      "chart_x": 3.88,
      "scores": {
        "innovation": 0.0,
        "adoption": 20.0,
        "narrative": 42.5,
        "risk": 22.5,
        "hype": 53.61
      },
      "consensus_note": "Framework maturation",
      "evidence_counts": {}
    },
    {
      "id": "evtol_operations_management",
      "name": "eVTOL Operations Management",
      "domain": "Operations",
      "phase": "Slope of Enlightenment",
      "phase_position": "early",
      "phase_confidence": 0.85,
      "chart_x": 2.94,
      "scores": {
        "innovation": 0.0,
        "adoption": 20.0,
        "narrative": 35.0,
        "risk": 20.0,
        "hype": 21.28
      },
      "consensus_note": "Operational framework development",
      "evidence_counts": {}
    },
    {
      "id": "uam_traffic_management",
      "name": "UAM Traffic Management",
      "domain": "Infrastructure",
      "phase": "Slope of Enlightenment",
      "phase_position": "early",
      "phase_confidence": 0.85,
      "chart_x": 2.8,
      "scores": {
        "innovation": 0.0,
        "adoption": 20.0,
        "narrative": 35.0,
        "risk": 20.0,
        "hype": 21.28
      },
      "consensus_note": "Critical infrastructure gap",
      "evidence_counts": {}
    },
    {
      "id": "electric_motor",
      "name": "Electric Motor",
      "domain": "Propulsion",
      "phase": "Slope of Enlightenment",
      "phase_position": "late",
      "phase_confidence": 0.85,
      "chart_x": 4.1,
      "scores": {
        "innovation": 10.0,
        "adoption": 10.0,
        "narrative": 45.0,
        "risk": 25.0,
        "hype": 52.37
      },
      "evidence_counts": {"papers": 3}
    },
    {
      "id": "rotor_control_system",
      "name": "Rotor Control System",
      "domain": "Control Systems",
      "phase": "Plateau of Productivity",
      "phase_position": "early",
      "phase_confidence": 0.65,
      "chart_x": 4.48,
      "scores": {
        "innovation": 15.0,
        "adoption": 15.0,
        "narrative": 35.0,
        "risk": 17.5,
        "hype": 30.54
      },
      "evidence_counts": {"patents": 1}
    },
    {
      "id": "online_optimization_flight_control_system",
      "name": "Online Optimization Flight Control System",
      "domain": "Control Systems",
      "phase": "Plateau of Productivity",
      "phase_position": "early",
      "phase_confidence": 0.55,
      "chart_x": 4.43,
      "scores": {
        "innovation": 15.0,
        "adoption": 15.0,
        "narrative": 32.5,
        "risk": 17.5,
        "hype": 32.93
      },
      "evidence_counts": {"patents": 2}
    },
    {
      "id": "model_based_systems_engineering_framework",
      "name": "Model Based Systems Engineering Framework",
      "domain": "Design Tools",
      "phase": "Plateau of Productivity",
      "phase_position": "early",
      "phase_confidence": 0.75,
      "chart_x": 4.4,
      "scores": {
        "innovation": 7.5,
        "adoption": 15.0,
        "narrative": 40.0,
        "risk": 20.0,
        "hype": 37.91
      },
      "consensus_note": "Design process maturation",
      "evidence_counts": {"papers": 1}
    },
    {
      "id": "evtol_battery_system",
      "name": "eVTOL Battery System",
      "domain": "Energy Storage",
      "phase": "Plateau of Productivity",
      "phase_position": "early",
      "phase_confidence": 0.85,
      "chart_x": 4.15,
      "scores": {
        "innovation": 5.0,
        "adoption": 10.0,
        "narrative": 45.0,
        "risk": 15.0,
        "hype": 54.45
      },
      "consensus_note": "Specialized battery solutions",
      "evidence_counts": {}
    },
    {
      "id": "acoustic_measurement_techniques",
      "name": "Acoustic Measurement Techniques",
      "domain": "Testing",
      "phase": "Plateau of Productivity",
      "phase_position": "early",
      "phase_confidence": 0.85,
      "chart_x": 4.57,
      "scores": {
        "innovation": 10.0,
        "adoption": 15.0,
        "narrative": 45.0,
        "risk": 17.5,
        "hype": 51.16
      },
      "consensus_note": "Noise certification critical",
      "evidence_counts": {"papers": 3}
    },
    {
      "id": "composite_material_technology",
      "name": "Composite Material Technology",
      "domain": "Materials",
      "phase": "Plateau of Productivity",
      "phase_position": "mid",
      "phase_confidence": 0.85,
      "chart_x": 4.63,
      "scores": {
        "innovation": 7.5,
        "adoption": 15.0,
        "narrative": 45.0,
        "risk": 17.5,
        "hype": 52.15
      },
      "consensus_note": "Mature manufacturing tech",
      "evidence_counts": {"papers": 1}
    },
    {
      "id": "vertiport_network",
      "name": "Vertiport Network",
      "domain": "Infrastructure",
      "phase": "Plateau of Productivity",
      "phase_position": "late",
      "phase_confidence": 0.85,
      "chart_x": 4.70,
      "scores": {
        "innovation": 5.0,
        "adoption": 15.0,
        "narrative": 45.0,
        "risk": 15.0,
        "hype": 53.48
      },
      "consensus_note": "Infrastructure deployment phase",
      "evidence_counts": {}
    },
    {
      "id": "sensing_and_perception_systems",
      "name": "Sensing And Perception Systems",
      "domain": "Autonomy",
      "phase": "Plateau of Productivity",
      "phase_position": "mid",
      "phase_confidence": 0.65,
      "chart_x": 4.53,
      "scores": {
        "innovation": 10.0,
        "adoption": 15.0,
        "narrative": 37.5,
        "risk": 15.0,
        "hype": 25.37
      },
      "evidence_counts": {"papers": 1}
    },
    {
      "id": "vtol_drive_system",
      "name": "VTOL Drive System",
      "domain": "Propulsion",
      "phase": "Plateau of Productivity",
      "phase_position": "late",
      "phase_confidence": 0.65,
      "chart_x": 4.63,
      "scores": {
        "innovation": 15.0,
        "adoption": 15.0,
        "narrative": 45.0,
        "risk": 15.0,
        "hype": 50.0
      },
      "consensus_note": "Mature VTOL mechanisms",
      "evidence_counts": {"patents": 1, "news": 17}
    },
    {
      "id": "hybrid_electric_propulsion",
      "name": "Hybrid Electric Propulsion",
      "domain": "Propulsion",
      "phase": "Plateau of Productivity",
      "phase_position": "late",
      "phase_confidence": 0.85,
      "chart_x": 4.87,
      "scores": {
        "innovation": 10.0,
        "adoption": 20.0,
        "narrative": 45.0,
        "risk": 20.0,
        "hype": 20.14
      },
      "consensus_note": "Proven hybrid architectures",
      "evidence_counts": {"papers": 2}
    },
    {
      "id": "lithium_ion_battery",
      "name": "Lithium Ion Battery",
      "domain": "Energy Storage",
      "phase": "Plateau of Productivity",
      "phase_position": "late",
      "phase_confidence": 0.85,
      "chart_x": 5,
      "scores": {
        "innovation": 10.0,
        "adoption": 20.0,
        "narrative": 45.0,
        "risk": 20.0,
        "hype": 20.14
      },
      "consensus_note": "Mature battery technology",
      "evidence_counts": {"papers": 4}
    }
  ],
  "analysis_summary": {
    "key_insights": [
      "Manufacturing breakthrough: Friction welding shows highest innovation potential (45/100)",
      "Reality gap: Peak technologies (air taxis, eVTOL networks) show 100% hype but <20% adoption",
      "Safety systems lag: Critical systems like Detect & Avoid stuck in trough phase",
      "Infrastructure emerging: Vertiports and charging infrastructure moving to productivity",
      "Power systems mature: Traditional lithium-ion batteries in late plateau phase"
    ],
    "risk_factors": [
      "High divergence between hype and adoption in peak technologies",
      "Critical safety systems underperforming expectations",
      "Infrastructure deployment lagging vehicle development",
      "Manufacturing technologies not scaling as expected"
    ],
    "opportunities": [
      "Friction welding manufacturing breakthrough could reduce costs",
      "Digital twin technology enabling better testing/validation",
      "Sustainable aviation practices gaining regulatory support",
      "Distributed electric propulsion architectures showing promise"
    ]
  }
}